places/__init__.py
places/add_environment.py
places/add_key.py
places/add_setting.py
places/add_variable.py
places/cli.py
places/decrypt.py
places/encrypt.py
places/generate_env.py
places/generate_key.py
places/init.py
places/places_utils.py
places/places_yaml.py
places/sync_gitignore.py
places/watch.py
places/templates/_e2e_test.yaml
places/templates/min.yaml
places/templates/tutorial.yaml
places/tests/__init__.py
places/tests/conftest.py
places/tests/test_utils.py
places/tests/cli/__init__.py
places/tests/cli/cli_test.py
places/tests/cli/expected_dir/.env
places/tests/cli/expected_dir/.env.dev
places/tests/cli/expected_dir/.env.prod
places/tests/cli/expected_dir/places.yaml
places/tests/cli/expected_dir/.places/places.enc.yaml
places/tests/cli/expected_dir/.places/keys/default
places/tests/cli/expected_dir/.places/keys/dev
places/tests/cli/expected_dir/.places/keys/prod
places/tests/cli/expected_dir/.places/keys/test
places/tests/e2e/__init__.py
places/tests/e2e/e2e_test.py
places/tests/e2e/expected_dir/.env
places/tests/e2e/expected_dir/.env.dev
places/tests/e2e/expected_dir/.env.prod
places/tests/e2e/expected_dir/places.yaml
places/tests/e2e/expected_dir/.places/places.enc.yaml
places/tests/e2e/expected_dir/.places/keys/default
places/tests/e2e/expected_dir/.places/keys/dev
places/tests/e2e/expected_dir/.places/keys/prod
places/tests/e2e/expected_dir/.places/keys/test
places_env-1.0.6.dist-info/licenses/LICENSE
places_env-1.0.6.dist-info/METADATA
places_env-1.0.6.dist-info/WHEEL
places_env-1.0.6.dist-info/entry_points.txt
places_env-1.0.6.dist-info/top_level.txt
places_env-1.0.6.dist-info/RECORD
