Metadata-Version: 2.4
Name: places-env
Version: 1.0.6
Summary: securely version control environment files
Author: Marc Krenn
Maintainer: Marc Krenn
License: MIT License
Project-URL: homepage, https://github.com/marckrenn/places-env
Project-URL: repository, https://github.com/marckrenn/places-env
Project-URL: issues, https://github.com/marckrenn/places-env/issues
Keywords: environments,environment variables,secrets,env,tool,infisical,dotenv,hashicorp,vault
Classifier: Programming Language :: Python :: 3
Classifier: Programming Language :: Python :: 3.11
Classifier: License :: OSI Approved :: MIT License
Classifier: Operating System :: OS Independent
Classifier: Development Status :: 3 - Alpha
Requires-Python: >=3.11
License-File: LICENSE
Requires-Dist: click==8.1.*
Requires-Dist: pyyaml==6.0.*
Requires-Dist: watchdog==6.0.*
Requires-Dist: cryptography==43.0.*
Requires-Dist: psutil==6.1.*
Requires-Dist: ruamel.yaml==0.18.*
Provides-Extra: dev
Requires-Dist: pytest==8.3.*; extra == "dev"
Requires-Dist: sphinx==8.1.*; extra == "dev"
Requires-Dist: sphinx-click==6.0.*; extra == "dev"
Requires-Dist: sphinx-markdown-builder>=0.6.7; extra == "dev"
Requires-Dist: black==24.10.*; extra == "dev"
Requires-Dist: pyflakes==3.2.*; extra == "dev"
Requires-Dist: twine==6.0.*; extra == "dev"
Dynamic: license-file
